finney/__init__.py
finney/cli.py
finney/domain_objects.py
finney/search.py
finney/data/domains.txt
finney/data/extensions.txt
finney/data/keywords.txt
finney/data/words.txt
finney/models/__init__.py
finney/models/decision_tree.py
finney/models/features.py
finney/models/grid_search.py
finney/models/intrinsic.py
finney-0.1.5.dist-info/licenses/LICENSE
finney-0.1.5.dist-info/METADATA
finney-0.1.5.dist-info/WHEEL
finney-0.1.5.dist-info/entry_points.txt
finney-0.1.5.dist-info/top_level.txt
finney-0.1.5.dist-info/RECORD
