Metadata-Version: 2.4
Name: finney
Version: 0.1.5
Summary: Pre-commit hook to make sure you don't accidentally push secrets
Author-email: Dany Lewin <danyglewin@gmail.com>, Ravid Prozan <ravidprozan@gmail.com>
License: Copyright (c) 2025 Ravid Prozan, Dany Lewin
Project-URL: Homepage, https://github.com/DanyGLewin/Finney/
Project-URL: Issues, https://github.com/DanyGLewin/Finney/issues
Classifier: Development Status :: 4 - Beta
Classifier: Environment :: Console
Classifier: Intended Audience :: Developers
Classifier: License :: OSI Approved :: MIT License
Classifier: Operating System :: OS Independent
Classifier: Programming Language :: Python :: 3
Classifier: Topic :: Software Development :: Quality Assurance
Classifier: Topic :: Software Development :: Version Control :: Git
Classifier: Typing :: Typed
Requires-Python: >=3.9
License-File: LICENSE
Requires-Dist: click
Requires-Dist: PyYAML
Requires-Dist: pandas
Requires-Dist: rich
Requires-Dist: pre-commit
Provides-Extra: dev
Requires-Dist: pre-commit; extra == "dev"
Requires-Dist: tensorflow; extra == "dev"
Requires-Dist: scikit-learn; extra == "dev"
Requires-Dist: xgboost; extra == "dev"
Dynamic: license-file
